spsdk_jlink/__init__.py
spsdk_jlink/probe.py
spsdk_jlink/__pyinstaller/__init__.py
spsdk_jlink/__pyinstaller/hook-spsdk_jlink.py
spsdk_jlink-0.3.0.dist-info/LICENSE
spsdk_jlink-0.3.0.dist-info/METADATA
spsdk_jlink-0.3.0.dist-info/WHEEL
spsdk_jlink-0.3.0.dist-info/entry_points.txt
spsdk_jlink-0.3.0.dist-info/top_level.txt
spsdk_jlink-0.3.0.dist-info/RECORD
